{
  "$schema": "https://json.schemastore.org/tsconfig",
  "display": "Default",
  "files": ["./process.d.ts"],
  "compilerOptions": {
    "composite": false,
    "declaration": true,
    "declarationMap": true,
    "esModuleInterop": true,
    "forceConsistentCasingInFileNames": true,
    "inlineSources": false,
    "isolatedModules": true,
    "moduleResolution": "node",
    "noUnusedLocals": false,
    "noUnusedParameters": false,
    "preserveWatchOutput": true,
    "skipLibCheck": true,
    "strict": false,
    "allowJs": true,
    "verbatimModuleSyntax": true,
    "incremental": true,
    "resolveJsonModule": true,
    "tsBuildInfoFile": ".tsbuildinfo"
  },
  "exclude": ["node_modules"]
}
